{
    "actions": [],
    "creation": "2026-03-12 00:00:00.000000",
    "doctype": "DocType",
    "editable_grid": 1,
    "engine": "InnoDB",
    "field_order": [
        "identificacion_section",
        "codigo_cifra",
        "concepto",
        "identificacion_column",
        "nivel",
        "formato_numero",
        "redondear_entero",
        "comentario",
        "calculo_section",
        "origen_dato",
        "es_manual",
        "calculo_column",
        "calculo_automatico",
        "formula_cifras",
        "presentacion_section",
        "no_imprimir",
        "negrita",
        "presentacion_column",
        "subrayado",
        "es_titulo",
        "es_linea_blanco",
        "es_total",
        "es_subtotal",
        "cursiva",
        "valores_section",
        "monto_actual",
        "valor_texto_actual",
        "valores_column",
        "monto_comparativo",
        "valor_texto_comparativo"
    ],
    "fields": [
        {"fieldname": "identificacion_section", "fieldtype": "Section Break", "label": "Identificacion"},
        {"fieldname": "codigo_cifra", "fieldtype": "Data", "label": "Codigo Cifra", "reqd": 1, "in_list_view": 1},
        {"fieldname": "concepto", "fieldtype": "Data", "label": "Concepto", "in_list_view": 1},
        {"fieldname": "identificacion_column", "fieldtype": "Column Break"},
        {"fieldname": "nivel", "fieldtype": "Int", "label": "Nivel", "default": 1},
        {"fieldname": "formato_numero", "fieldtype": "Select", "label": "Formato Numero", "options": "Numero\nMoneda\nPorcentaje\nTexto", "default": "Moneda"},
        {"fieldname": "redondear_entero", "fieldtype": "Check", "label": "Redondear Entero", "default": 0},
        {"fieldname": "comentario", "fieldtype": "Small Text", "label": "Comentario"},
        {"fieldname": "calculo_section", "fieldtype": "Section Break", "label": "Origen y Calculo"},
        {"fieldname": "origen_dato", "fieldtype": "Select", "label": "Origen Dato", "options": "Manual\nBalanza\nFormula", "default": "Manual"},
        {"fieldname": "es_manual", "fieldtype": "Check", "label": "Es Manual", "default": 0},
        {"fieldname": "calculo_column", "fieldtype": "Column Break"},
        {"fieldname": "calculo_automatico", "fieldtype": "Check", "label": "Calculo Automatico", "default": 0},
        {
            "fieldname": "formula_cifras",
            "fieldtype": "Small Text",
            "label": "Formula Cifras",
            "description": "Usa codigos de cifra separados por coma, punto y coma o salto de linea. Puedes anteponer + o -. Ejemplo: ACTIVO_CORRIENTE,-PASIVO_CORRIENTE"
        },
        {"fieldname": "presentacion_section", "fieldtype": "Section Break", "label": "Presentacion"},
        {"fieldname": "no_imprimir", "fieldtype": "Check", "label": "No Imprimir", "default": 0},
        {"fieldname": "negrita", "fieldtype": "Check", "label": "Negrita", "default": 0},
        {"fieldname": "presentacion_column", "fieldtype": "Column Break"},
        {"fieldname": "subrayado", "fieldtype": "Check", "label": "Subrayado", "default": 0},
        {"fieldname": "es_titulo", "fieldtype": "Check", "label": "Es Titulo", "default": 0},
        {"fieldname": "es_linea_blanco", "fieldtype": "Check", "label": "Es Linea en Blanco", "default": 0},
        {"fieldname": "es_total", "fieldtype": "Check", "label": "Es Total", "default": 0},
        {"fieldname": "es_subtotal", "fieldtype": "Check", "label": "Es Subtotal", "default": 0},
        {"fieldname": "cursiva", "fieldtype": "Check", "label": "Cursiva", "default": 0},
        {"fieldname": "valores_section", "fieldtype": "Section Break", "label": "Valores"},
        {"fieldname": "monto_actual", "fieldtype": "Float", "label": "Monto Actual", "in_list_view": 1},
        {"fieldname": "valor_texto_actual", "fieldtype": "Data", "label": "Valor Texto Actual", "depends_on": "eval:doc.formato_numero=='Texto'"},
        {"fieldname": "valores_column", "fieldtype": "Column Break"},
        {"fieldname": "monto_comparativo", "fieldtype": "Float", "label": "Monto Comparativo", "in_list_view": 1},
        {"fieldname": "valor_texto_comparativo", "fieldtype": "Data", "label": "Valor Texto Comparativo", "depends_on": "eval:doc.formato_numero=='Texto'"}
    ],
    "istable": 1,
    "module": "MFI Tools",
    "name": "Cifra Nota EEFF",
    "permissions": [],
    "sort_field": "modified",
    "sort_order": "DESC"
}
